kimoby/__init__.py
kimoby/kimoby.py
kimoby-0.0.8.dist-info/METADATA
kimoby-0.0.8.dist-info/WHEEL
kimoby-0.0.8.dist-info/top_level.txt
kimoby-0.0.8.dist-info/RECORD
