Metadata-Version: 2.1
Name: kimoby
Version: 0.0.8
Summary: Python module to interact with the Kimoby REST API
Home-page: https://github.com/regg00/kimoby
Author: Régis Tremblay Lefrançois
Author-email: regg00@gmail.com
License: UNKNOWN
Project-URL: Bug Tracker, https://github.com/regg00/kimoby/issues
Platform: UNKNOWN
Classifier: Programming Language :: Python :: 3
Classifier: License :: OSI Approved :: MIT License
Classifier: Operating System :: OS Independent
Requires-Python: >=3.6
Requires-Dist: requests
Requires-Dist: phonenumbers
